{"cameraMode":{"drawMode":0,"name":"Shaded","section":"Shading Mode"},"sceneLighting":true,"audioPlay":false,"sceneViewState":{"m_AlwaysRefresh":false,"showFog":true,"showSkybox":true,"showFlares":true,"showImageEffects":true,"showParticleSystems":true,"showVisualEffectGraphs":true,"m_FxEnabled":true},"in2DMode":false,"pivot":{"x":41.73713302612305,"y":-8.930279731750489,"z":10.334329605102539},"rotation":{"x":0.23627321422100068,"y":0.5214455723762512,"z":-0.15294654667377473,"w":0.805536687374115},"size":10.0,"orthographic":false}